cbu_tools/__init__.py
cbu_tools/src/__init__.py
cbu_tools/src/cbu.py
cbu_tools-1.0.0.dist-info/LICENSE.txt
cbu_tools-1.0.0.dist-info/METADATA
cbu_tools-1.0.0.dist-info/WHEEL
cbu_tools-1.0.0.dist-info/top_level.txt
cbu_tools-1.0.0.dist-info/RECORD
