Metadata-Version: 2.1
Name: cbu_tools
Version: 1.0.0
Summary: A package for working with Clave Bancaria Uniforme (CBU)
Home-page: https://github.com/jifernandezv/cbu-tools
Author: Juan Fernández
Author-email: jifernandezv97@gmail.com
Keywords: cbu,clave bancaria uniforme,argentina,banco,validador,bank,validator
Classifier: Programming Language :: Python :: 3
Classifier: License :: OSI Approved :: MIT License
Requires-Python: >=3.6
License-File: LICENSE.txt
